neuronautics/__init__.py
neuronautics/main.py
neuronautics/my_resources.py
neuronautics/analysis/__init__.py
neuronautics/analysis/analysis-base.yml
neuronautics/analysis/analysis_creator.py
neuronautics/analysis/helpers.py
neuronautics/analysis/loader.py
neuronautics/analysis/correlation/__init__.py
neuronautics/analysis/correlation/activity_correlation.py
neuronautics/analysis/correlation/spike_time_tiling_coefficient.py
neuronautics/analysis/templates/__init__.py
neuronautics/analysis/templates/bar-analysis.jinja
neuronautics/analysis/templates/base-analysis.jinja
neuronautics/analysis/templates/graph-analysis.jinja
neuronautics/analysis/templates/image-analysis.jinja
neuronautics/analysis/templates/line-analysis.jinja
neuronautics/analysis/type/__init__.py
neuronautics/analysis/type/abstract_analysis.py
neuronautics/analysis/type/bar_analysis.py
neuronautics/analysis/type/graph_analysis.py
neuronautics/analysis/type/image_analysis.py
neuronautics/analysis/type/line_analysis.py
neuronautics/analysis/type/misc_analysis.py
neuronautics/analysis/type/palette.py
neuronautics/config/__init__.py
neuronautics/config/layout.py
neuronautics/config/settings.py
neuronautics/mlkit/__init__.py
neuronautics/mlkit/spike_sorter.py
neuronautics/plotters/__init__.py
neuronautics/plotters/grid_line_2d.py
neuronautics/plotters/line_2d.py
neuronautics/plotters/mini_line_2d.py
neuronautics/plotters/widgets/__init__.py
neuronautics/plotters/widgets/signal_line.py
neuronautics/plotters/widgets/signal_unit_selector.py
neuronautics/plotters/widgets/signal_view_selector.py
neuronautics/recordings/__init__.py
neuronautics/recordings/abstract_raw.py
neuronautics/recordings/abstract_spike.py
neuronautics/recordings/config.py
neuronautics/recordings/mcs_raw.py
neuronautics/recordings/nn_spike.py
neuronautics/ui/__init__.py
neuronautics/ui/abstract_source.py
neuronautics/ui/analysis-creation.ui
neuronautics/ui/analysis_ui.py
neuronautics/ui/code-error.ui
neuronautics/ui/code_error_ui.py
neuronautics-0.2.1.dist-info/LICENSE
neuronautics-0.2.1.dist-info/METADATA
neuronautics-0.2.1.dist-info/WHEEL
neuronautics-0.2.1.dist-info/entry_points.txt
neuronautics-0.2.1.dist-info/top_level.txt
neuronautics-0.2.1.dist-info/RECORD
