Metadata-Version: 2.1
Name: neuronautics
Version: 0.2.1
Summary: Simplify the exploration of neural data.
Author: Daniel de Santos Sierra
Author-email: desantossierra@gmail.com
License: GNU General
Keywords: one,two
Classifier: Programming Language :: Python :: 3
Classifier: Development Status :: 2 - Pre-Alpha
Classifier: Environment :: X11 Applications :: Qt
Requires-Python: >=3.10
License-File: LICENSE
Requires-Dist: pyqt5
Requires-Dist: PyQtChart
Requires-Dist: numpy
Requires-Dist: pandas
Requires-Dist: matplotlib
Requires-Dist: McsPyDataTools
Requires-Dist: scikit-learn
Requires-Dist: pyyaml
Requires-Dist: jinja2
Requires-Dist: networkx
Requires-Dist: neo
Requires-Dist: elephant
